queryanonymizer/__init__.py
queryanonymizer/keywords.json
queryanonymizer-1.1.4.dist-info/LICENSE
queryanonymizer-1.1.4.dist-info/METADATA
queryanonymizer-1.1.4.dist-info/WHEEL
queryanonymizer-1.1.4.dist-info/top_level.txt
queryanonymizer-1.1.4.dist-info/RECORD
