Metadata-Version: 2.1
Name: queryanonymizer
Version: 1.1.4
Summary: A Python library for anonymizing queries like SQL, DAX etc. or other text.
Home-page: https://github.com/datateampl/queryanonymizer
Author: Mariusz Cieciura, Mateusz Cieciura
Author-email: contact@datateam.pl
License: MIT
Project-URL: Homepage, https://queryanonymizer.com
Project-URL: Source, https://github.com/datateampl/queryanonymizer
Classifier: Development Status :: 5 - Production/Stable
Classifier: Intended Audience :: Developers
Classifier: License :: OSI Approved :: MIT License
Classifier: Programming Language :: Python :: 3.8
Classifier: Programming Language :: Python :: 3.9
Classifier: Programming Language :: Python :: 3.10
Classifier: Programming Language :: Python :: 3.11
Classifier: Programming Language :: Python :: 3.12
Classifier: Operating System :: OS Independent
Requires-Python: >=3.8
License-File: LICENSE
Requires-Dist: python-dateutil
Requires-Dist: unidecode
